csdn/__init__.py
csdn/aFunc.py
csdn_mzh-0.4.dist-info/LICENSE.txt
csdn_mzh-0.4.dist-info/METADATA
csdn_mzh-0.4.dist-info/WHEEL
csdn_mzh-0.4.dist-info/top_level.txt
csdn_mzh-0.4.dist-info/RECORD
